done/__init__.py
done/done.py
done/public/check-empty.png
done/public/check-full.png
done/static/css/done.css
done/static/js/src/done.js
done/templates/done.html
done/templates/studioview.html
done_xblock-2.5.0.dist-info/LICENSE
done_xblock-2.5.0.dist-info/METADATA
done_xblock-2.5.0.dist-info/NOTICE
done_xblock-2.5.0.dist-info/WHEEL
done_xblock-2.5.0.dist-info/entry_points.txt
done_xblock-2.5.0.dist-info/top_level.txt
done_xblock-2.5.0.dist-info/RECORD
