Metadata-Version: 2.1
Name: done-xblock
Version: 2.5.0
Summary: done XBlock
Home-page: https://github.com/openedx/DoneXBlock
Classifier: Programming Language :: Python :: 3
Classifier: Programming Language :: Python :: 3.11
Classifier: Programming Language :: Python :: 3.12
License-File: LICENSE
License-File: NOTICE
Requires-Dist: XBlock
Requires-Dist: django
